qqg/__init__.py
qqg/models.py
qqg/search.py
qqg-0.0.2.dist-info/LICENSE
qqg-0.0.2.dist-info/METADATA
qqg-0.0.2.dist-info/WHEEL
qqg-0.0.2.dist-info/entry_points.txt
qqg-0.0.2.dist-info/top_level.txt
qqg-0.0.2.dist-info/RECORD
