Metadata-Version: 2.1
Name: qqg
Version: 0.0.2
Summary: A small CLI search tool
Author-email: Emil Kloeden <emilkloeden@gmail.com>
Project-URL: Homepage, https://github.com/emilkloeden/qqg
Project-URL: Bug Tracker, https://github.com/emilkloeden/qqg/issues
Classifier: Programming Language :: Python :: 3
Classifier: License :: OSI Approved :: MIT License
Classifier: Operating System :: OS Independent
Requires-Python: >=3.10
License-File: LICENSE
Requires-Dist: beautifulsoup4 (==4.12.2)
Requires-Dist: requests (==2.28.2)
Requires-Dist: markdownify (==0.11.6)
